visier/__init__.py
visier/sdk/__init__.py
visier/sdk/api/__init__.py
visier/sdk/api/model_query/__init__.py
visier/sdk/api/model_query/api_client.py
visier/sdk/api/model_query/api_response.py
visier/sdk/api/model_query/configuration.py
visier/sdk/api/model_query/exceptions.py
visier/sdk/api/model_query/py.typed
visier/sdk/api/model_query/rest.py
visier/sdk/api/model_query/api/__init__.py
visier/sdk/api/model_query/api/data_model_api.py
visier/sdk/api/model_query/api/query_api.py
visier/sdk/api/model_query/models/__init__.py
visier/sdk/api/model_query/models/aggregation_query_dto.py
visier/sdk/api/model_query/models/aggregation_query_execution_dto.py
visier/sdk/api/model_query/models/aggregation_query_source_dto.py
visier/sdk/api/model_query/models/aggregation_query_source_metric_dto.py
visier/sdk/api/model_query/models/aggregation_query_source_metrics_dto.py
visier/sdk/api/model_query/models/aggregation_type_option_dto.py
visier/sdk/api/model_query/models/aggregation_type_parameter_dto.py
visier/sdk/api/model_query/models/aggregation_type_parameter_value_dto.py
visier/sdk/api/model_query/models/analytic_object_dto.py
visier/sdk/api/model_query/models/analytic_objects_dto.py
visier/sdk/api/model_query/models/cell_distribution_bin_dto.py
visier/sdk/api/model_query/models/cell_distribution_options_dto.py
visier/sdk/api/model_query/models/cell_dto.py
visier/sdk/api/model_query/models/cell_set_axis_dto.py
visier/sdk/api/model_query/models/cell_set_axis_position_dto.py
visier/sdk/api/model_query/models/cell_set_dto.py
visier/sdk/api/model_query/models/cohort_filter_dto.py
visier/sdk/api/model_query/models/currencies_dto.py
visier/sdk/api/model_query/models/currency_dto.py
visier/sdk/api/model_query/models/currency_rate_dto.py
visier/sdk/api/model_query/models/currency_rates_dto.py
visier/sdk/api/model_query/models/dimension_dto.py
visier/sdk/api/model_query/models/dimension_mapping_validation_dto.py
visier.sdk.api.model_query-0.0.3.dist-info/METADATA
visier.sdk.api.model_query-0.0.3.dist-info/WHEEL
visier.sdk.api.model_query-0.0.3.dist-info/top_level.txt
visier.sdk.api.model_query-0.0.3.dist-info/RECORD
