Metadata-Version: 2.1
Name: visier.sdk.api.model-query
Version: 0.0.3
Summary: Visier Public Platform APIs
Home-page: UNKNOWN
Author: OpenAPI Generator community
Author-email: team@openapitools.org
License: Apache License, Version 2.0
Keywords: OpenAPI,OpenAPI-Generator,Visier Public Platform APIs
Platform: UNKNOWN
Requires-Dist: pydantic (>=2)
Requires-Dist: python-dateutil
Requires-Dist: typing-extensions (>=4.7.1)
Requires-Dist: urllib3 (<2.1.0,>=1.25.3)
